COPYING
MANIFEST.in
README.rst
memory_profiler.py
mprof.py
setup.py
memory_profiler.egg-info/PKG-INFO
memory_profiler.egg-info/SOURCES.txt
memory_profiler.egg-info/dependency_links.txt
memory_profiler.egg-info/entry_points.txt
memory_profiler.egg-info/requires.txt
memory_profiler.egg-info/top_level.txt
test/test_as.py
test/test_async.py
test/test_attributes.py
test/test_exception.py
test/test_exit_code.py
test/test_func.py
test/test_gen.py
test/test_global.py
test/test_import.py
test/test_increment_display.py
test/test_loop.py
test/test_loop_decorated.py
test/test_memory_usage.py
test/test_mprof.py
test/test_mprofile.py
test/test_nested.py
test/test_precision_command_line.py
test/test_precision_import.py
test/test_stream_unicode.py
test/test_tracemalloc.py
test/test_unicode.py