Metadata-Version: 1.2
Name: memory_profiler
Version: 0.60.0
Summary: A module for monitoring memory usage of a python program
Home-page: https://github.com/pythonprofilers/memory_profiler
Author: Fabian Pedregosa
Author-email: f@bianp.net
License: BSD
Platform: UNKNOWN
Classifier: Development Status :: 5 - Production/Stable
Classifier: Intended Audience :: Science/Research
Classifier: Intended Audience :: Developers
Classifier: License :: OSI Approved :: BSD License
Classifier: Programming Language :: Python
Classifier: Programming Language :: Python :: 3
Classifier: Topic :: Software Development
Classifier: Operating System :: POSIX
Classifier: Operating System :: Unix
Requires-Python: >=3.4
